vvv_rpc_server/Awake.exe
vvv_rpc_server/__init__.py
vvv_rpc_server/main.js
vvv_rpc_server/main.kfcvme50
vvv_rpc_server/main_linux.kfcvme50
vvv_rpc_server-0.3.4.dist-info/METADATA
vvv_rpc_server-0.3.4.dist-info/WHEEL
vvv_rpc_server-0.3.4.dist-info/entry_points.txt
vvv_rpc_server-0.3.4.dist-info/top_level.txt
vvv_rpc_server-0.3.4.dist-info/RECORD
