Metadata-Version: 2.1
Name: vvv-rpc-server
Version: 0.3.4
Requires-Python: >=3.5
Requires-Dist: vvv-rpc
Requires-Dist: vvv-rpc-server-stable>=0.0.1
